{"entries":{"https://github.com/paritytech/parity-signer/commit/ea5786c85661d9b176795b9386af640b3e73aff3":{"timestamp":{"secs_since_epoch":1635158811,"nanos_since_epoch":388735791},"valid":true},"https://github.com/paritytech/parity-signer/releases/":{"timestamp":{"secs_since_epoch":1635158810,"nanos_since_epoch":366082715},"valid":true},"https://github.com/paritytech/parity-signer/tree/legacy-metadataRN":{"timestamp":{"secs_since_epoch":1635158810,"nanos_since_epoch":760716239},"valid":true},"https://github.com/paritytech/parity-signer/releases":{"timestamp":{"secs_since_epoch":1635158811,"nanos_since_epoch":459816900},"valid":true},"https://github.com/w3f/schnorrkel":{"timestamp":{"secs_since_epoch":1635158811,"nanos_since_epoch":724838955},"valid":true},"https://github.com/bitcoin/bips/blob/master/bip-0032.mediawiki/":{"timestamp":{"secs_since_epoch":1635158811,"nanos_since_epoch":828536011},"valid":true},"https://itunes.apple.com/us/app/parity-signer/id1218174838":{"timestamp":{"secs_since_epoch":1635158810,"nanos_since_epoch":691848874},"valid":true},"https://wiki.polkadot.network/docs/en/learn-keys":{"timestamp":{"secs_since_epoch":1635158811,"nanos_since_epoch":572498634},"valid":true},"https://play.google.com/store/apps/details?id=io.parity.signer":{"timestamp":{"secs_since_epoch":1635158809,"nanos_since_epoch":997920616},"valid":true},"https://substrate.dev/docs/en/knowledgebase/integrate/subkey":{"timestamp":{"secs_since_epoch":1635158810,"nanos_since_epoch":124031316},"valid":true},"https://github.com/paritytech/parity-signer/wiki/HDKD-on-Parity-Signer#hdkd-general-on-substrate":{"timestamp":{"secs_since_epoch":1635158812,"nanos_since_epoch":188621250},"valid":true},"https://github.com/maciejhirsz/uos":{"timestamp":{"secs_since_epoch":1635158810,"nanos_since_epoch":906072821},"valid":true},"https://github.com/paritytech/parity-signer/tree/legacy-4.6.2":{"timestamp":{"secs_since_epoch":1635158810,"nanos_since_epoch":207244666},"valid":true},"https://github.com/paritytech/parity-signer/tree/legacy-4.5.3":{"timestamp":{"secs_since_epoch":1635158810,"nanos_since_epoch":185639038},"valid":true},"https://polkadot.js.org/apps":{"timestamp":{"secs_since_epoch":1635158809,"nanos_since_epoch":907495623},"valid":true},"https://blog.rust-lang.org/2020/01/03/reducing-support-for-32-bit-apple-targets.html":{"timestamp":{"secs_since_epoch":1635158810,"nanos_since_epoch":969369576},"valid":true},"https://developer.android.com/ndk/downloads":{"timestamp":{"secs_since_epoch":1635158811,"nanos_since_epoch":267596889},"valid":true},"https://appstoreconnect.apple.com/":{"timestamp":{"secs_since_epoch":1635158811,"nanos_since_epoch":207433596},"valid":true},"https://github.com/paritytech/parity-signer/tree/legacy-rust":{"timestamp":{"secs_since_epoch":1635158810,"nanos_since_epoch":187818581},"valid":true},"https://polkadot.js.org/apps/":{"timestamp":{"secs_since_epoch":1635158811,"nanos_since_epoch":503031357},"valid":true}}}