{"entries":{"https://polkadot.js.org/apps":{"timestamp":{"secs_since_epoch":1639070993,"nanos_since_epoch":472983390},"valid":true},"https://itunes.apple.com/us/app/parity-signer/id1218174838":{"timestamp":{"secs_since_epoch":1639070994,"nanos_since_epoch":273069289},"valid":true},"https://appstoreconnect.apple.com/":{"timestamp":{"secs_since_epoch":1639070994,"nanos_since_epoch":727337344},"valid":true},"https://play.google.com/store/apps/details?id=io.parity.signer":{"timestamp":{"secs_since_epoch":1639070993,"nanos_since_epoch":549429920},"valid":true},"https://github.com/maciejhirsz/uos":{"timestamp":{"secs_since_epoch":1639070993,"nanos_since_epoch":792468087},"valid":true},"https://github.com/paritytech/parity-signer/releases/":{"timestamp":{"secs_since_epoch":1639070994,"nanos_since_epoch":106283151},"valid":true},"https://github.com/paritytech/parity-signer/releases":{"timestamp":{"secs_since_epoch":1639070995,"nanos_since_epoch":44443828},"valid":true},"https://github.com/paritytech/parity-signer/tree/legacy-4.5.3":{"timestamp":{"secs_since_epoch":1639070993,"nanos_since_epoch":658640634},"valid":true},"https://github.com/paritytech/parity-signer/tree/legacy-4.6.2":{"timestamp":{"secs_since_epoch":1639070993,"nanos_since_epoch":646170964},"valid":true},"https://github.com/paritytech/parity-signer/commit/ea5786c85661d9b176795b9386af640b3e73aff3":{"timestamp":{"secs_since_epoch":1639070994,"nanos_since_epoch":909333268},"valid":true},"https://developer.android.com/ndk/downloads":{"timestamp":{"secs_since_epoch":1639070996,"nanos_since_epoch":92583822},"valid":true},"https://github.com/paritytech/parity-signer/tree/legacy-rust":{"timestamp":{"secs_since_epoch":1639070993,"nanos_since_epoch":660023042},"valid":true},"https://substrate.dev/docs/en/knowledgebase/integrate/subkey":{"timestamp":{"secs_since_epoch":1639070994,"nanos_since_epoch":243681524},"valid":true},"https://github.com/paritytech/parity-signer/wiki/HDKD-on-Parity-Signer#hdkd-general-on-substrate":{"timestamp":{"secs_since_epoch":1639070994,"nanos_since_epoch":603706749},"valid":true},"https://wiki.polkadot.network/docs/en/learn-keys":{"timestamp":{"secs_since_epoch":1639070994,"nanos_since_epoch":471836007},"valid":true},"https://github.com/paritytech/parity-signer/tree/legacy-metadataRN":{"timestamp":{"secs_since_epoch":1639070993,"nanos_since_epoch":639324725},"valid":true},"https://polkadot.js.org/apps/":{"timestamp":{"secs_since_epoch":1639070994,"nanos_since_epoch":352674837},"valid":true},"https://blog.rust-lang.org/2020/01/03/reducing-support-for-32-bit-apple-targets.html":{"timestamp":{"secs_since_epoch":1639070994,"nanos_since_epoch":682963995},"valid":true},"https://github.com/w3f/schnorrkel":{"timestamp":{"secs_since_epoch":1639070994,"nanos_since_epoch":531289542},"valid":true},"https://github.com/bitcoin/bips/blob/master/bip-0032.mediawiki/":{"timestamp":{"secs_since_epoch":1639070994,"nanos_since_epoch":489042204},"valid":true}}}