{"entries":{"https://github.com/paritytech/parity-signer/releases/":{"timestamp":{"secs_since_epoch":1635273940,"nanos_since_epoch":749783692},"valid":true},"https://github.com/paritytech/parity-signer/wiki/HDKD-on-Parity-Signer#hdkd-general-on-substrate":{"timestamp":{"secs_since_epoch":1635273940,"nanos_since_epoch":372850884},"valid":true},"https://github.com/paritytech/parity-signer/commit/ea5786c85661d9b176795b9386af640b3e73aff3":{"timestamp":{"secs_since_epoch":1635273938,"nanos_since_epoch":453593434},"valid":true},"https://polkadot.js.org/apps":{"timestamp":{"secs_since_epoch":1635273940,"nanos_since_epoch":484183336},"valid":true},"https://github.com/paritytech/parity-signer/tree/legacy-rust":{"timestamp":{"secs_since_epoch":1635273940,"nanos_since_epoch":837725507},"valid":true},"https://developer.android.com/ndk/downloads":{"timestamp":{"secs_since_epoch":1635273940,"nanos_since_epoch":77294642},"valid":true},"https://github.com/paritytech/parity-signer/tree/legacy-4.5.3":{"timestamp":{"secs_since_epoch":1635273940,"nanos_since_epoch":828823554},"valid":true},"https://polkadot.js.org/apps/":{"timestamp":{"secs_since_epoch":1635273940,"nanos_since_epoch":156253209},"valid":true},"https://blog.rust-lang.org/2020/01/03/reducing-support-for-32-bit-apple-targets.html":{"timestamp":{"secs_since_epoch":1635273938,"nanos_since_epoch":138602170},"valid":true},"https://github.com/paritytech/parity-signer/releases":{"timestamp":{"secs_since_epoch":1635273938,"nanos_since_epoch":657666341},"valid":true},"https://substrate.dev/docs/en/knowledgebase/integrate/subkey":{"timestamp":{"secs_since_epoch":1635273940,"nanos_since_epoch":343876615},"valid":true},"https://github.com/maciejhirsz/uos":{"timestamp":{"secs_since_epoch":1635273940,"nanos_since_epoch":715646492},"valid":true},"https://github.com/paritytech/parity-signer/tree/legacy-4.6.2":{"timestamp":{"secs_since_epoch":1635273940,"nanos_since_epoch":825347034},"valid":true},"https://itunes.apple.com/us/app/parity-signer/id1218174838":{"timestamp":{"secs_since_epoch":1635273939,"nanos_since_epoch":605671},"valid":true},"https://github.com/w3f/schnorrkel":{"timestamp":{"secs_since_epoch":1635273940,"nanos_since_epoch":402350457},"valid":true},"https://github.com/bitcoin/bips/blob/master/bip-0032.mediawiki/":{"timestamp":{"secs_since_epoch":1635273940,"nanos_since_epoch":311781927},"valid":true},"https://appstoreconnect.apple.com/":{"timestamp":{"secs_since_epoch":1635273938,"nanos_since_epoch":390844162},"valid":true},"https://wiki.polkadot.network/docs/en/learn-keys":{"timestamp":{"secs_since_epoch":1635273940,"nanos_since_epoch":202177181},"valid":true},"https://play.google.com/store/apps/details?id=io.parity.signer":{"timestamp":{"secs_since_epoch":1635273938,"nanos_since_epoch":301253432},"valid":true},"https://github.com/paritytech/parity-signer/tree/legacy-metadataRN":{"timestamp":{"secs_since_epoch":1635273940,"nanos_since_epoch":748905386},"valid":true}}}